orkg/__init__.py
orkg/client/__init__.py
orkg/client/backend.py
orkg/client/classes.py
orkg/client/comparisons.py
orkg/client/contribution_comparisons.py
orkg/client/contributions.py
orkg/client/dummy.py
orkg/client/fields.py
orkg/client/harvesters/__init__.py
orkg/client/harvesters/directory.py
orkg/client/harvesters/doi.py
orkg/client/harvesters/harvesters.py
orkg/client/harvesters/utils.py
orkg/client/json.py
orkg/client/lists.py
orkg/client/literals.py
orkg/client/objects.py
orkg/client/papers.py
orkg/client/predicates.py
orkg/client/problems.py
orkg/client/resources.py
orkg/client/session.py
orkg/client/snapshots.py
orkg/client/statements.py
orkg/client/stats.py
orkg/client/templates/__init__.py
orkg/client/templates/codegen.py
orkg/client/templates/components.py
orkg/client/templates/out.py
orkg/client/templates/statements.py
orkg/client/templates/templates.py
orkg/client/templates/utils.py
orkg/common.py
orkg/convert.py
orkg/errors.py
orkg/graph/__init__.py
orkg/graph/subgraph.py
orkg/logging_config.py
orkg/logging_messages.py
orkg/out.py
orkg/utils.py
orkg/version.py
orkg-1.2.0.dist-info/LICENSE
orkg-1.2.0.dist-info/METADATA
orkg-1.2.0.dist-info/WHEEL
orkg-1.2.0.dist-info/RECORD
