Metadata-Version: 2.1
Name: orkg
Version: 1.2.0
Summary: The official python client for the Open Research Knowledge Graph (ORKG) API
Home-page: http://orkg.org/about
License: MIT
Keywords: ORKG,Scholarly Communication,Digital Library,API Wrapper,Python Client
Author: Yaser Jaradeh
Author-email: yaser.jaradeh@tib.eu
Maintainer: Yaser Jaradeh
Requires-Python: >=3.9,<4.0
Classifier: Development Status :: 4 - Beta
Classifier: Intended Audience :: Developers
Classifier: License :: OSI Approved :: MIT License
Classifier: Programming Language :: Python :: 3
Classifier: Programming Language :: Python :: 3.9
Classifier: Programming Language :: Python :: 3.10
Classifier: Programming Language :: Python :: 3.11
Classifier: Programming Language :: Python :: 3.12
Classifier: Programming Language :: Python :: 3.13
Classifier: Topic :: Software Development :: Build Tools
Requires-Dist: Deprecated (>=1.2.14,<2.0.0)
Requires-Dist: Faker (>=19.1.0,<20.0.0)
Requires-Dist: Inflector (>=3.1.0,<4.0.0)
Requires-Dist: cardinality (>=0.1.1,<0.2.0)
Requires-Dist: hammock (>=0.2.4,<0.3.0)
Requires-Dist: loguru (>=0.7.2,<0.8.0)
Requires-Dist: networkx (>=3.1,<4.0)
Requires-Dist: pandas (>=2.0.1,<3.0.0)
Requires-Dist: pydantic (>=2.0.3,<3.0.0)
Requires-Dist: python-keycloak (>=5.7.0,<6.0.0)
Requires-Dist: requests (>=2.31.0,<3.0.0)
Requires-Dist: tqdm (>=4.65.0,<5.0.0)
Requires-Dist: undecorated (>=0.3.0,<0.4.0)
Project-URL: Documentation, https://orkg.readthedocs.io/en/latest/
Project-URL: Repository, https://gitlab.com/TIBHannover/orkg/orkg-pypi
